{
  "required": true,
  "package": "io.github.betterthanupdates.forge.mixin",
  "mixins": [
    "block.BlockMixin",
    "block.ButtonBlockMixin",
    "block.ChestBlockMixin",
    "block.DoorBlockMixin",
    "block.LadderBlockMixin",
    "block.LeverBlockMixin",
    "block.PressurePlateBlockMixin",
    "block.RailBlockMixin",
    "block.RedstoneDustBlockMixin",
    "block.RedstoneRepeaterBlockMixin",
    "block.TorchBlockMixin",
    "block.TrapdoorBlockMixin",
    "container.slot.CraftingResultSlotMixin",
    "entity.LivingEntityMixin",
    "entity.player.PlayerEntityMixin",
    "item.BucketItemMixin",
    "item.ItemMixin",
    "util.hit.HitResultMixin",
    "world.explosion.ExplosionMixin",
    "world.WorldMixin",
    "world.chunk.ChunkMixin"
  ],
  "client": [
    "client.BlockRendererMixin",
    "client.ClientInteractionManagerMixin",
    "client.GameRendererMixin",
    "client.MultiplayerClientInteractionManagerMixin",
    "client.ParticleManagerMixin",
    "client.PistonRendererMixin",
    "client.PlayerRendererMixin",
    "client.TessellatorMixin",
    "client.TextureManagerMixin"
  ],
  "server": [
    "server.class_417Mixin",
    "server.item.ToolItemMixin",
    "server.server.ServerPlayerView_class_514Mixin",
    "server.server.player.ServerInteractionManagerMixin"
  ],
  "plugin": "io.github.betterthanupdates.apron.ApronMixinPlugin",
  "parent": "apron.parent.mixins.json"
}
